.gitignore
README.md
buildout.cfg
setup.py
colorizer/__init__.py
colorizer.egg-info/PKG-INFO
colorizer.egg-info/SOURCES.txt
colorizer.egg-info/dependency_links.txt
colorizer.egg-info/entry_points.txt
colorizer.egg-info/requires.txt
colorizer.egg-info/top_level.txt