Metadata-Version: 1.0
Name: colorizer
Version: 0.1.6
Summary: Console colorizer, which acts like grep but paint each match in it's own color.
Home-page: http://github.com/svetlyak40wt/colorizer/
Author: Alexander Artemenko
Author-email: svetlyak.40wt@gmail.com
License: New BSD License
Platform: UNKNOWN
Classifier: Environment :: Console
Classifier: Operating System :: POSIX
Classifier: Operating System :: MacOS :: MacOS X
Classifier: Intended Audience :: Developers
Classifier: Intended Audience :: System Administrators
Classifier: Programming Language :: Python
